simple_ai_manager/__init__.py
simple_ai_manager/ai_manager.py
simple_ai_manager/services/__init__.py
simple_ai_manager/services/anthropic_service.py
simple_ai_manager/services/google_service.py
simple_ai_manager/services/groq_service.py
simple_ai_manager/services/openai_service.py
simple_ai_manager-0.1.6.dist-info/METADATA
simple_ai_manager-0.1.6.dist-info/WHEEL
simple_ai_manager-0.1.6.dist-info/top_level.txt
simple_ai_manager-0.1.6.dist-info/RECORD
