Metadata-Version: 2.1
Name: simple_ai_manager
Version: 0.1.6
Summary: A common management module for AI generation services
Home-page: https://github.com/555happy/AI_Manager
Author: 555happy
Author-email: 555happy.jp@gmail.com
Classifier: Programming Language :: Python :: 3
Classifier: License :: OSI Approved :: MIT License
Classifier: Operating System :: OS Independent
Requires-Python: >=3.6
Requires-Dist: python-dotenv
Requires-Dist: openai
Requires-Dist: google-generativeai
Requires-Dist: anthropic
Requires-Dist: groq
